skontol/__init__.py
skontol/cli.py
skontol/clis/__init__.py
skontol/clis/base.py
skontol/clis/masukin.py
skontol-2.1.3.dist-info/METADATA
skontol-2.1.3.dist-info/WHEEL
skontol-2.1.3.dist-info/entry_points.txt
skontol-2.1.3.dist-info/top_level.txt
skontol-2.1.3.dist-info/RECORD
