Metadata-Version: 2.1
Name: skontol
Version: 2.1.3
Summary: skontol from kontol
Home-page: https://github.com/IrfanDect/skontol
Author: stytyd
Author-email: stytyd@gmail.com
License: join now
Keywords: skontol_cli
Classifier: Intended Audience :: Developers
Classifier: Topic :: Utilities
Classifier: License :: Public Domain
Classifier: Natural Language :: English
Classifier: Operating System :: OS Independent
Classifier: Programming Language :: Python :: 3
Classifier: Programming Language :: Python :: 3.2
Classifier: Programming Language :: Python :: 3.3
Classifier: Programming Language :: Python :: 3.4
Classifier: Programming Language :: Python :: 3.5
Classifier: Programming Language :: Python :: 3.6
Requires-Dist: setuptools
Requires-Dist: docopt
Provides-Extra: test
Requires-Dist: coverage ; extra == 'test'
Requires-Dist: pytest ; extra == 'test'
Requires-Dist: pytest-cov ; extra == 'test'
Requires-Dist: pytest-ordering ; extra == 'test'
Requires-Dist: rich ; extra == 'test'
Requires-Dist: testfixtures ; extra == 'test'
